setup.cfg
setup.py
kdense/__init__.py
kdense/approximate_kernel_density.py
kdense/util.py
kdense/version.py
kdense.egg-info/PKG-INFO
kdense.egg-info/SOURCES.txt
kdense.egg-info/dependency_links.txt
kdense.egg-info/pbr.json
kdense.egg-info/requires.txt
kdense.egg-info/top_level.txt
kdense.egg-info/zip-safe