Metadata-Version: 1.0
Name: kdense
Version: 1.0.0
Summary: Efficient kernel density estimation for numpy+scipy.
Home-page: http://github.com/scivey/kdense
Author: Scott Ivey
Author-email: scott.ivey@gmail.com
License: UNKNOWN
Platform: UNKNOWN
